scop/__init__.py
scop/py.typed
scop/scop-linux
scop/scop-mac
scop/scop-win.exe
scop/scop.py
scop-0.1.0.dist-info/METADATA
scop-0.1.0.dist-info/WHEEL
scop-0.1.0.dist-info/licenses/LICENSE
scop-0.1.0.dist-info/RECORD
