Metadata-Version: 2.4
Name: scop
Version: 0.1.0
Summary: Constraint Programming Solver SCOP
Author-email: Mikio Kubo <kubo@kaiyodai.ac.jp>, Saito Tsutomu <tsutomu7@hotmail.co.jp>
License: Apache-2.0
License-File: LICENSE
Requires-Python: >=3.10
Requires-Dist: plotly>=5.24.1
